py2d_game/__init__.py
py2d_game/audio.py
py2d_game/cli.py
py2d_game/core.py
py2d_game/graphics.py
py2d_game/input.py
py2d_game/physics.py
py2d_game/ui.py
py2d_game/utils.py
py2d_game-1.0.0b0.dist-info/licenses/LICENSE
py2d_game-1.0.0b0.dist-info/METADATA
py2d_game-1.0.0b0.dist-info/WHEEL
py2d_game-1.0.0b0.dist-info/entry_points.txt
py2d_game-1.0.0b0.dist-info/top_level.txt
py2d_game-1.0.0b0.dist-info/RECORD
