Metadata-Version: 2.4
Name: py2d-game
Version: 1.0.0b0
Summary: A powerful and easy-to-use Python library for creating 2D games
Author: En-Hussain
Author-email: En-Hussain <support@py2d-game.com>
Maintainer-email: En-Hussain <support@py2d-game.com>
License: MIT
Project-URL: Homepage, https://github.com/En-Hussain/py2d-game
Project-URL: Documentation, https://github.com/En-Hussain/py2d-game#readme
Project-URL: Repository, https://github.com/En-Hussain/py2d-game.git
Project-URL: Issues, https://github.com/En-Hussain/py2d-game/issues
Project-URL: Changelog, https://github.com/En-Hussain/py2d-game/blob/main/CHANGELOG.md
Keywords: game,2d,pygame,engine,development,python
Classifier: Development Status :: 4 - Beta
Classifier: Intended Audience :: Developers
Classifier: License :: OSI Approved :: MIT License
Classifier: Operating System :: OS Independent
Classifier: Programming Language :: Python :: 3
Classifier: Programming Language :: Python :: 3.7
Classifier: Programming Language :: Python :: 3.8
Classifier: Programming Language :: Python :: 3.9
Classifier: Programming Language :: Python :: 3.10
Classifier: Programming Language :: Python :: 3.11
Classifier: Programming Language :: Python :: 3.12
Classifier: Topic :: Games/Entertainment
Classifier: Topic :: Software Development :: Libraries :: Python Modules
Requires-Python: >=3.7
License-File: LICENSE
Requires-Dist: pygame>=2.0.0
Provides-Extra: dev
Requires-Dist: pytest>=6.0; extra == "dev"
Requires-Dist: pytest-cov>=2.0; extra == "dev"
Requires-Dist: black>=21.0; extra == "dev"
Requires-Dist: flake8>=3.8; extra == "dev"
Dynamic: author
Dynamic: license-file
Dynamic: requires-python
